papi/__init__.py
papi/base.py
papi/contexts.py
papi/edges.py
papi/nodes.py
papi/py.typed
papi/utils.py
valohai_papi-0.1.3.dist-info/LICENSE
valohai_papi-0.1.3.dist-info/WHEEL
valohai_papi-0.1.3.dist-info/METADATA
valohai_papi-0.1.3.dist-info/RECORD
